puzzle_solver/__init__.py
puzzle_solver/core/utils.py
puzzle_solver/core/utils_ortools.py
puzzle_solver/puzzles/aquarium/aquarium.py
puzzle_solver/puzzles/battleships/battleships.py
puzzle_solver/puzzles/binairo/binairo.py
puzzle_solver/puzzles/black_box/black_box.py
puzzle_solver/puzzles/bridges/bridges.py
puzzle_solver/puzzles/chess_range/chess_melee.py
puzzle_solver/puzzles/chess_range/chess_range.py
puzzle_solver/puzzles/chess_range/chess_solo.py
puzzle_solver/puzzles/chess_sequence/chess_sequence.py
puzzle_solver/puzzles/dominosa/dominosa.py
puzzle_solver/puzzles/filling/filling.py
puzzle_solver/puzzles/galaxies/galaxies.py
puzzle_solver/puzzles/galaxies/parse_map/parse_map.py
puzzle_solver/puzzles/guess/guess.py
puzzle_solver/puzzles/inertia/inertia.py
puzzle_solver/puzzles/inertia/tsp.py
puzzle_solver/puzzles/inertia/parse_map/parse_map.py
puzzle_solver/puzzles/kakurasu/kakurasu.py
puzzle_solver/puzzles/keen/keen.py
puzzle_solver/puzzles/light_up/light_up.py
puzzle_solver/puzzles/lits/lits.py
puzzle_solver/puzzles/magnets/magnets.py
puzzle_solver/puzzles/map/map.py
puzzle_solver/puzzles/minesweeper/minesweeper.py
puzzle_solver/puzzles/mosaic/mosaic.py
puzzle_solver/puzzles/nonograms/nonograms.py
puzzle_solver/puzzles/norinori/norinori.py
puzzle_solver/puzzles/pearl/pearl.py
puzzle_solver/puzzles/range/range.py
puzzle_solver/puzzles/rectangles/rectangles.py
puzzle_solver/puzzles/signpost/signpost.py
puzzle_solver/puzzles/singles/singles.py
puzzle_solver/puzzles/slant/slant.py
puzzle_solver/puzzles/slant/parse_map/parse_map.py
puzzle_solver/puzzles/slitherlink/slitherlink.py
puzzle_solver/puzzles/star_battle/star_battle.py
puzzle_solver/puzzles/star_battle/star_battle_shapeless.py
puzzle_solver/puzzles/stitches/stitches.py
puzzle_solver/puzzles/stitches/parse_map/parse_map.py
puzzle_solver/puzzles/sudoku/sudoku.py
puzzle_solver/puzzles/tents/tents.py
puzzle_solver/puzzles/thermometers/thermometers.py
puzzle_solver/puzzles/towers/towers.py
multi_puzzle_solver-0.9.24.dist-info/METADATA
multi_puzzle_solver-0.9.24.dist-info/WHEEL
multi_puzzle_solver-0.9.24.dist-info/top_level.txt
multi_puzzle_solver-0.9.24.dist-info/RECORD
