Metadata-Version: 2.4
Name: multi-puzzle-solver
Version: 0.9.24
Summary: Efficient solvers for numerous popular and esoteric logic puzzles using CP-SAT
Author: Ar-Kareem
Project-URL: Homepage, https://github.com/Ar-Kareem/puzzle_solver
Project-URL: Repository, https://github.com/Ar-Kareem/puzzle_solver
Project-URL: Issues, https://github.com/Ar-Kareem/puzzle_solver/issues
Keywords: puzzle,solver,sat,cp-sat,google-or-tools,efficient,logic,puzzle-solver,puzzle-solver-python,sudoku,nonograms,minesweeper,dominosa,lightup,map,inertia,tents,towers,tracks,undead,unruly,bridges,pearl,range,signpost,singles,magnets
Classifier: Development Status :: 4 - Beta
Classifier: Intended Audience :: Developers
Classifier: Intended Audience :: Education
Classifier: Intended Audience :: Science/Research
Classifier: Programming Language :: Python :: 3.9
Classifier: Programming Language :: Python :: 3.10
Classifier: Programming Language :: Python :: 3.11
Classifier: Programming Language :: Python :: 3.12
Classifier: Programming Language :: Python :: 3.13
Requires-Python: >=3.9
Requires-Dist: numpy
Requires-Dist: ortools
Provides-Extra: dev
Requires-Dist: pytest; extra == "dev"
Requires-Dist: pytest-xdist; extra == "dev"
